{"name": "KI4ETA-Tree", "enabled": true, "referencedServerId": "1319", "referencedServerName": "OPC UA Simulation Server", "referencedRootNodeId": "ns=3;s=85/0:Simulation", "mappings": [{"browsePath": "3:Random", "name": "Random", "measurementCreation": {"unit": "V", "type": "ka", "fragmentName": "c8y_strom0", "series": "Strom0"}}, {"browsePath": "0:ServerDiagnosticsSummary", "name": "ServerDiagnosticsSummary", "measurementCreation": {"unit": "V", "type": "ka", "fragmentName": "c8y_strom1", "series": "Strom1"}}, {"browsePath": "3:Counter", "name": "Counter", "measurementCreation": {"unit": "V", "type": "ka", "fragmentName": "c8y_strom2", "series": "Strom2"}}, {"browsePath": "3:Square", "name": "Square", "measurementCreation": {"unit": "V", "type": "ka", "fragmentName": "c8y_strom3", "series": "Strom3"}}, {"browsePath": "0:ServerStatus", "name": "ServerStatus", "measurementCreation": {"unit": "V", "type": "ka", "fragmentName": "c8y_strom4", "series": "Strom4"}}, {"browsePath": "0:SessionDiagnosticsArray", "name": "SessionDiagnosticsArray", "measurementCreation": {"unit": "V", "type": "ka", "fragmentName": "c8y_strom5", "series": "Strom5"}}, {"browsePath": "6:MyLevel", "name": "MyLevel", "measurementCreation": {"unit": "V", "type": "ka", "fragmentName": "c8y_strom6", "series": "Strom6"}}, {"browsePath": "6:MyLevel", "name": "MyLevel", "measurementCreation": {"unit": "V", "type": "ka", "fragmentName": "c8y_strom7", "series": "Strom7"}}, {"browsePath": "6:MyLevel", "name": "MyLevel", "measurementCreation": {"unit": "V", "type": "ka", "fragmentName": "c8y_strom8", "series": "Strom8"}}, {"browsePath": "0:SessionSecurityDiagnosticsArray", "name": "SessionSecurityDiagnosticsArray", "measurementCreation": {"unit": "V", "type": "ka", "fragmentName": "c8y_strom9", "series": "Strom9"}}, {"browsePath": "0:SessionDiagnostics", "name": "SessionDiagnostics", "measurementCreation": {"unit": "V", "type": "ka", "fragmentName": "c8y_strom10", "series": "Strom10"}}, {"browsePath": "3:Sinusoid", "name": "Sinusoid", "measurementCreation": {"unit": "V", "type": "ka", "fragmentName": "c8y_strom11", "series": "Strom11"}}, {"browsePath": "6:MyLevel", "name": "MyLevel", "measurementCreation": {"unit": "V", "type": "ka", "fragmentName": "c8y_strom12", "series": "Strom12"}}, {"browsePath": "3:Sawtooth", "name": "Sawtooth", "measurementCreation": {"unit": "V", "type": "ka", "fragmentName": "c8y_strom13", "series": "Strom13"}}, {"browsePath": "6:MyLevel", "name": "MyLevel", "measurementCreation": {"unit": "V", "type": "ka", "fragmentName": "c8y_strom14", "series": "Strom14"}}, {"browsePath": "6:MyLevel", "name": "MyLevel", "measurementCreation": {"unit": "V", "type": "ka", "fragmentName": "c8y_strom15", "series": "Strom15"}}, {"browsePath": "3:Triangle", "name": "Triangle", "measurementCreation": {"unit": "V", "type": "ka", "fragmentName": "c8y_strom16", "series": "Strom16"}}, {"browsePath": "6:MyLevel", "name": "MyLevel", "measurementCreation": {"unit": "V", "type": "ka", "fragmentName": "c8y_strom17", "series": "Strom17"}}, {"browsePath": "0:SessionDiagnostics", "name": "SessionDiagnostics", "measurementCreation": {"unit": "V", "type": "ka", "fragmentName": "c8y_strom18", "series": "Strom18"}}, {"browsePath": "6:MyLevel", "name": "MyLevel", "measurementCreation": {"unit": "V", "type": "ka", "fragmentName": "c8y_strom19", "series": "Strom19"}}], "subscriptionType": {"type": "Subscription", "subscriptionParameters": {"samplingRate": 5000}}}